vsc_solvers/__init__.py
vsc_solvers/pkginfo.py
vsc_solvers/__build_num__.py
vsc_solvers/core.cpython-39-x86_64-linux-gnu.so
vsc_solvers/share/include/vsc/solvers/SolveFlags.h
vsc_solvers/share/include/vsc/solvers/ISolverFactory.h
vsc_solvers/share/include/vsc/solvers/FactoryExt.h
vsc_solvers/share/include/vsc/solvers/IRandomizer.h
vsc_solvers/share/include/vsc/solvers/ICompoundSolver.h
vsc_solvers/share/include/vsc/solvers/SolveFlagsSet.h
vsc_solvers/share/include/vsc/solvers/ISolver.h
vsc_solvers/share/include/vsc/solvers/ISolveSet.h
vsc_solvers/share/include/vsc/solvers/IFactory.h
vsc_solvers/share/include/vsc/solvers/IRandState.h
vsc_solvers/share/include/vsc/solvers/impl/RefPathSet.h
vsc_solvers/share/include/vsc/solvers/impl/TaskUnrollModelFieldRefConstraints.h
vsc_solvers/share/include/vsc/solvers/impl/RefPathConstraint.h
vsc_solvers/share/include/vsc/solvers/impl/TaskPath2ValRef.h
vsc_solvers/share/include/vsc/solvers/impl/RefPathMap.h
vsc_solvers/share/include/vsc/solvers/impl/RefPathPtrMap.h
vsc_solvers/share/include/vsc/solvers/impl/TaskPath2Field.h
vsc_solvers/share/include/vsc/solvers/impl/RefPathField.h
vsc_solvers/share/include/vsc/solvers/impl/TaskPath2Constraint.h
vsc_solvers/share/include/vsc/solvers/impl/BuildConstraintVisitor.h
vsc_solvers/share/include/vsc/solvers/impl/TaskUnrollModelIterativeConstraints.h
vsc_solvers-0.0.1.8469955330.dist-info/RECORD
vsc_solvers-0.0.1.8469955330.dist-info/entry_points.txt
vsc_solvers-0.0.1.8469955330.dist-info/METADATA
vsc_solvers-0.0.1.8469955330.dist-info/WHEEL
vsc_solvers-0.0.1.8469955330.dist-info/top_level.txt
vsc_solvers-0.0.1.8469955330.dist-info/LICENSE
