Metadata-Version: 2.1
Name: vsc-solvers
Version: 0.0.1.8469955330
Summary: Core Verification Stimulus and Coverage library
Home-page: https://github.com/vsc-tools/vsc-solvers
Author: Matthew Ballance
Author-email: matt.ballance@gmail.com
License: Apache 2.0
Keywords: SystemVerilog,Verilog,RTL,Python
License-File: LICENSE
Requires-Dist: vsc-dm
